lanxinplus_openapi/__init__.py
lanxinplus_openapi/api_client.py
lanxinplus_openapi/configuration.py
lanxinplus_openapi/exceptions.py
lanxinplus_openapi/model_utils.py
lanxinplus_openapi/rest.py
lanxinplus_openapi/api/__init__.py
lanxinplus_openapi/api/addrbk_department_api.py
lanxinplus_openapi/api/addrbk_staff_api.py
lanxinplus_openapi/api/addrbk_tags_api.py
lanxinplus_openapi/api/appmge_api.py
lanxinplus_openapi/api/auth_api.py
lanxinplus_openapi/api/media_api.py
lanxinplus_openapi/api/message_api.py
lanxinplus_openapi/api/org_api.py
lanxinplus_openapi/api/role_api.py
lanxinplus_openapi/apis/__init__.py
lanxinplus_openapi/model/__init__.py
lanxinplus_openapi/model/ancestor_department.py
lanxinplus_openapi/model/app_roaming_org_list.py
lanxinplus_openapi/model/base_response.py
lanxinplus_openapi/model/department.py
lanxinplus_openapi/model/department_data.py
lanxinplus_openapi/model/department_staff_info.py
lanxinplus_openapi/model/event.py
lanxinplus_openapi/model/extra_field_id.py
lanxinplus_openapi/model/group_info_tag.py
lanxinplus_openapi/model/introduction.py
lanxinplus_openapi/model/mobile_phone.py
lanxinplus_openapi/model/push_data.py
lanxinplus_openapi/model/resume.py
lanxinplus_openapi/model/role_staff.py
lanxinplus_openapi/model/search_scope.py
lanxinplus_openapi/model/search_staff_info.py
lanxinplus_openapi/model/status_info.py
lanxinplus_openapi/model/system_msg.py
lanxinplus_openapi/model/tag_filter.py
lanxinplus_openapi/model/tag_meta.py
lanxinplus_openapi/model/tag_staff_info.py
lanxinplus_openapi/model/u_department.py
lanxinplus_openapi/model/v1_app_roaming_orgs_fetch_data.py
lanxinplus_openapi/model/v1_app_roaming_orgs_fetch_response.py
lanxinplus_openapi/model/v1_app_token_create_data.py
lanxinplus_openapi/model/v1_app_token_create_response.py
lanxinplus_openapi/model/v1_chat_notification_fetch_data.py
lanxinplus_openapi/model/v1_chat_notification_fetch_response.py
lanxinplus_openapi/model/v1_depts_children_fetch_data.py
lanxinplus_openapi-1.0.0.4.dist-info/LICENSE
lanxinplus_openapi-1.0.0.4.dist-info/METADATA
lanxinplus_openapi-1.0.0.4.dist-info/WHEEL
lanxinplus_openapi-1.0.0.4.dist-info/top_level.txt
lanxinplus_openapi-1.0.0.4.dist-info/RECORD
