Metadata-Version: 2.1
Name: lanxinplus-openapi
Version: 1.0.0.4
Summary: LanXin+ OpenAPI
Home-page: UNKNOWN
Author: API Support
Author-email: open@comisys.net
License: UNKNOWN
Keywords: LanXin+ OpenAPI
Platform: UNKNOWN
Requires-Python: >=3.6
License-File: LICENSE
Requires-Dist: urllib3 (>=1.25.3)
Requires-Dist: python-dateutil
